pylinkbotd
